Pymath/PyMathFunc.py
Pymath/__init__.py
PyMath_Stable-0.0.20.dist-info/License.md
PyMath_Stable-0.0.20.dist-info/METADATA
PyMath_Stable-0.0.20.dist-info/WHEEL
PyMath_Stable-0.0.20.dist-info/top_level.txt
PyMath_Stable-0.0.20.dist-info/RECORD
