Metadata-Version: 2.1
Name: PyMath-Stable
Version: 0.0.20
Summary: Extra Mathmatics for python
Author: Inan
Author-email: <abdulhakim.sabuj@gmail.com>
Keywords: python,Math,Mathmatics
Classifier: Development Status :: 1 - Planning
Classifier: Intended Audience :: Developers
Classifier: Programming Language :: Python :: 3
Classifier: Operating System :: Unix
Classifier: Operating System :: MacOS :: MacOS X
Classifier: Operating System :: Microsoft :: Windows
License-File: License.md
